<WorkflowConfig Version="14.0.0.6109">
	<Template BaseID="{8F7E73D2-695B-429F-B9A3-1840F337B065}" DocLibID="{$ListId:Workflows;}" XomlHref="Workflows/Create Workorder List Item/Create Workorder List Item.xoml" XomlVersion="V1.0" TaskContentType="0x01080100C9C9515DE4E24001905074F980F93160" Category="List" Name="Create Workorder List Item" Description=""/>
	<Association ListID="{$ListId:Workorder Library;}" TaskListID="{$ListId:Lists/Tasks;}" HistoryListID="{$ListId:Lists/Workflow History;}" StartOnCreate="true"/>
	<ContentTypes/>
	<Initiation URL="_layouts/IniWrkflIP.aspx">
		<Fields/>
		<Parameters/>
		<DefaultData/>
	</Initiation>
	<Extended>
		<Fields/>
	</Extended>
	<MetaData>
		<ExtendedStatusColumnValues>
			<StatusColumnValue>Canceled</StatusColumnValue>
			<StatusColumnValue>Approved</StatusColumnValue>
			<StatusColumnValue>Rejected</StatusColumnValue>
		</ExtendedStatusColumnValues>
		<Instantiation_FormURI>Workflows/Create Workorder List Item/Create Workorder List Item.xsn</Instantiation_FormURI>
	</MetaData>
</WorkflowConfig>
